collectd_connect_time
