Metadata-Version: 1.1
Name: collectd-connect-time
Version: 0.2.2
Summary: TCP Connection time plugin for collectd.
Home-page: http://github.com/makefu/collectd-connect-time
Author: Felix Richter
Author-email: github@syntax-fehler.de
License: wtfpl
Platform: UNKNOWN
Classifier: Development Status :: 3 - Alpha
